lightning_factory/DatAnalysisTool.py
lightning_factory/LightningFactory.py
lightning_factory/__init__.py
lightning_factory/create_ffnn.py
lightning_factory/enums.py
lightning_factory/functions.py
tests/__init__.py
tests/test_create_ffnn.py
tests/test_lightning_factory.py
tests/test_lightning_factory_constructor.py
tests/test_merge_parameters_with_default.py
lightning_factory-0.1.3.dist-info/LICENSE.txt
lightning_factory-0.1.3.dist-info/METADATA
lightning_factory-0.1.3.dist-info/WHEEL
lightning_factory-0.1.3.dist-info/top_level.txt
lightning_factory-0.1.3.dist-info/RECORD
