Metadata-Version: 2.1
Name: lightning-factory
Version: 0.1.3
Summary: Quickly, with very little code, create PyTorch Lightning models
Home-page: https://github.com/brianrisk/lightning_factory
Author: Brian Risk
Author-email: brian@d.at
License: Apache License 2.0
Platform: UNKNOWN
Classifier: Development Status :: 3 - Alpha
Classifier: Intended Audience :: Developers
Classifier: License :: OSI Approved :: Apache Software License
Classifier: Natural Language :: English
Classifier: Programming Language :: Python :: 3.6
Classifier: Programming Language :: Python :: 3.7
Classifier: Programming Language :: Python :: 3.8
Classifier: Programming Language :: Python :: 3.9
Classifier: Operating System :: OS Independent
Requires-Python: >=3.6
License-File: LICENSE.txt
Requires-Dist: torch ==2.1.0
Requires-Dist: pytorch-lightning ==2.1.1
Requires-Dist: coverage
Requires-Dist: setuptools ~=60.2.0
Requires-Dist: pandas ~=2.0.3
Requires-Dist: scikit-learn ~=1.3.1
Requires-Dist: scipy ~=1.10.1
